<odoo>
    <menuitem id="menu_saas_root" name="SaaS Manager" sequence="10" groups="odoo_saas_manager.group_saas_support,odoo_saas_manager.group_saas_accountant,odoo_saas_manager.group_saas_manager,odoo_saas_manager.group_saas_admin"/>
    <menuitem id="menu_saas_operations" name="Operations" parent="menu_saas_root" sequence="10"/>
    <menuitem id="menu_saas_configuration" name="Configuration" parent="menu_saas_root" sequence="90"/>

    <menuitem id="menu_saas_dashboard" name="Dashboard" parent="menu_saas_root" action="action_saas_dashboard" sequence="1"/>
    <menuitem id="menu_saas_tenant" name="Tenants" parent="menu_saas_operations" action="action_saas_tenant" sequence="10"/>
    <menuitem id="menu_saas_subscription" name="Subscriptions" parent="menu_saas_operations" action="action_saas_subscription" sequence="20"/>
    <menuitem id="menu_saas_payment" name="Payments" parent="menu_saas_operations" action="action_saas_payment" sequence="30"/>
    <menuitem id="menu_saas_provisioning_log" name="Provisioning Logs" parent="menu_saas_operations" action="action_saas_provisioning_log" sequence="40"/>
    <menuitem id="menu_saas_onboarding_import" name="Onboarding Import" parent="menu_saas_operations" action="action_saas_onboarding_import_wizard" sequence="50"/>
    <menuitem id="menu_saas_plan" name="Plans" parent="menu_saas_configuration" action="action_saas_plan" sequence="10"/>
</odoo>
